{
    "node_list": [
        {
            "id": "post0",
            "url": "blank",
            "position": [
                63.2178849992747,
                -27.42316722215973,
                173.94158239076773
            ],
            "color": "#00FF00",
            "type": "post",
            "connected_node": [
                "category378"
            ]
        },
        {
            "id": "post1",
            "url": "blank",
            "position": [
                58.258731146814895,
                -22.881838000780334,
                175.8330007865211
            ],
            "color": "#00FF00",
            "type": "post",
            "connected_node": [
                "category378"
            ]
        },
        {
            "id": "post2",
            "url": "blank",
            "position": [
                56.50259686866926,
                -29.984680754668148,
                175.58600509247273
            ],
            "color": "#00FF00",
            "type": "post",
            "connected_node": [
                "category378"
            ]
        },
        {
            "id": "post3",
            "url": "blank",
            "position": [
                55.56094364573861,
                -26.474230910983547,
                177.42453709331468
            ],
            "color": "#00FF00",
            "type": "post",
            "connected_node": [
                "category378"
            ]
        },
        {
            "id": "post4",
            "url": "blank",
            "position": [
                61.55748002015702,
                -31.645027959034145,
                175.39204222972091
            ],
            "color": "#00FF00",
            "type": "post",
            "connected_node": [
                "category378"
            ]
        },
        {
            "id": "post5",
            "url": "blank",
            "position": [
                57.14334482992782,
                -19.71970593021743,
                178.43690812966656
            ],
            "color": "#00FF00",
            "type": "post",
            "connected_node": [
                "category378"
            ]
        },
        {
            "id": "post6",
            "url": "blank",
            "position": [
                65.34057008785955,
                -20.33703226623103,
                172.047575529393
            ],
            "color": "#00FF00",
            "type": "post",
            "connected_node": [
                "category378"
            ]
        },
        {
            "id": "post7",
            "url": "blank",
            "position": [
                56.98595441687028,
                -36.36525512787214,
                177.3819682285511
            ],
            "color": "#00FF00",
            "type": "post",
            "connected_node": [
                "category378"
            ]
        },
        {
            "id": "post8",
            "url": "blank",
            "position": [
                52.81782213968951,
                -20.92611187652793,
                179.2736344791642
            ],
            "color": "#00FF00",
            "type": "post",
            "connected_node": [
                "category378"
            ]
        },
        {
            "id": "post9",
            "url": "blank",
            "position": [
                61.16420524175312,
                -16.449376857207195,
                173.37470848724504
            ],
            "color": "#00FF00",
            "type": "post",
            "connected_node": [
                "category378"
            ]
        },
        {
            "id": "post10",
            "url": "blank",
            "position": [
                67.98902720412242,
                -31.12941563702969,
                171.7164952739884
            ],
            "color": "#00FF00",
            "type": "post",
            "connected_node": [
                "category378"
            ]
        },
        {
            "id": "post11",
            "url": "blank",
            "position": [
                52.61905454363482,
                -29.54755505963542,
                178.79778614168487
            ],
            "color": "#00FF00",
            "type": "post",
            "connected_node": [
                "category378"
            ]
        },
        {
            "id": "post12",
            "url": "blank",
            "position": [
                69.07097497846105,
                -24.400783189283047,
                172.8129321923298
            ],
            "color": "#00FF00",
            "type": "post",
            "connected_node": [
                "category378"
            ]
        },
        {
            "id": "post13",
            "url": "blank",
            "position": [
                48.216421055040385,
                -25.667806731528593,
                179.75007092798262
            ],
            "color": "#00FF00",
            "type": "post",
            "connected_node": [
                "category378"
            ]
        },
        {
            "id": "post14",
            "url": "blank",
            "position": [
                65.28388329310383,
                -37.690299344008736,
                174.73788356052114
            ],
            "color": "#00FF00",
            "type": "post",
            "connected_node": [
                "category378"
            ]
        },
        {
            "id": "post15",
            "url": "blank",
            "position": [
                52.975999740873846,
                -35.7284222381729,
                172.72887838754568
            ],
            "color": "#00FF00",
            "type": "post",
            "connected_node": [
                "category378"
            ]
        },
        {
            "id": "post16",
            "url": "blank",
            "position": [
                59.33094011150851,
                -14.613313571134064,
                178.16125496459438
            ],
            "color": "#00FF00",
            "type": "post",
            "connected_node": [
                "category378"
            ]
        },
        {
            "id": "post17",
            "url": "blank",
            "position": [
                52.89073174447122,
                -15.423294183938925,
                179.94730096054965
            ],
            "color": "#00FF00",
            "type": "post",
            "connected_node": [
                "category378"
            ]
        },
        {
            "id": "post18",
            "url": "blank",
            "position": [
                63.30992047506408,
                -15.65853755187699,
                179.42204271726834
            ],
            "color": "#00FF00",
            "type": "post",
            "connected_node": [
                "category378"
            ]
        },
        {
            "id": "post19",
            "url": "blank",
            "position": [
                60.37201908529257,
                -40.29707904198443,
                169.87489152625955
            ],
            "color": "#00FF00",
            "type": "post",
            "connected_node": [
                "category378"
            ]
        },
        {
            "id": "post20",
            "url": "blank",
            "position": [
                49.86491956611774,
                -32.493626416361195,
                181.09635074689663
            ],
            "color": "#00FF00",
            "type": "post",
            "connected_node": [
                "category378"
            ]
        },
        {
            "id": "post21",
            "url": "blank",
            "position": [
                63.849991601699706,
                -38.32367569648582,
                170.0340851200636
            ],
            "color": "#00FF00",
            "type": "post",
            "connected_node": [
                "category378"
            ]
        },
        {
            "id": "post22",
            "url": "blank",
            "position": [
                72.01173676705271,
                -30.898937003796075,
                170.73622448028755
            ],
            "color": "#00FF00",
            "type": "post",
            "connected_node": [
                "category378"
            ]
        },
        {
            "id": "post23",
            "url": "blank",
            "position": [
                63.11098751479903,
                -12.599620336984026,
                173.2556870177452
            ],
            "color": "#00FF00",
            "type": "post",
            "connected_node": [
                "category378"
            ]
        },
        {
            "id": "post24",
            "url": "blank",
            "position": [
                72.91280492682826,
                -21.97203684774017,
                172.3156513099862
            ],
            "color": "#00FF00",
            "type": "post",
            "connected_node": [
                "category378"
            ]
        },
        {
            "id": "post25",
            "url": "blank",
            "position": [
                48.253101287045226,
                -17.94802698562613,
                179.78344246167222
            ],
            "color": "#00FF00",
            "type": "post",
            "connected_node": [
                "category378"
            ]
        },
        {
            "id": "post26",
            "url": "blank",
            "position": [
                56.985419141379644,
                -39.100274994899195,
                171.67122787968307
            ],
            "color": "#00FF00",
            "type": "post",
            "connected_node": [
                "category378"
            ]
        },
        {
            "id": "post27",
            "url": "blank",
            "position": [
                70.5920330886685,
                -37.88382841519161,
                169.211946887472
            ],
            "color": "#00FF00",
            "type": "post",
            "connected_node": [
                "category378"
            ]
        },
        {
            "id": "post28",
            "url": "blank",
            "position": [
                70.22881292705195,
                -13.567736294230082,
                173.35802925725648
            ],
            "color": "#00FF00",
            "type": "post",
            "connected_node": [
                "category378"
            ]
        },
        {
            "id": "post29",
            "url": "blank",
            "position": [
                43.76769359625621,
                -31.574538385681034,
                179.22242838884793
            ],
            "color": "#00FF00",
            "type": "post",
            "connected_node": [
                "category378"
            ]
        },
        {
            "id": "post30",
            "url": "blank",
            "position": [
                47.18746735956507,
                -36.228492855047364,
                181.89889082495074
            ],
            "color": "#00FF00",
            "type": "post",
            "connected_node": [
                "category378"
            ]
        },
        {
            "id": "post31",
            "url": "blank",
            "position": [
                47.406280857099595,
                -33.79119225552247,
                174.59523715933537
            ],
            "color": "#00FF00",
            "type": "post",
            "connected_node": [
                "category378"
            ]
        },
        {
            "id": "post32",
            "url": "blank",
            "position": [
                68.25478744504287,
                -14.695307626087661,
                177.7892561554114
            ],
            "color": "#00FF00",
            "type": "post",
            "connected_node": [
                "category378"
            ]
        },
        {
            "id": "post33",
            "url": "blank",
            "position": [
                60.31360880075207,
                -10.604409573100888,
                182.67824815808626
            ],
            "color": "#00FF00",
            "type": "post",
            "connected_node": [
                "category378"
            ]
        },
        {
            "id": "post34",
            "url": "blank",
            "position": [
                76.82403882476002,
                -22.068818389184223,
                169.02825869535855
            ],
            "color": "#00FF00",
            "type": "post",
            "connected_node": [
                "category378"
            ]
        },
        {
            "id": "post35",
            "url": "blank",
            "position": [
                65.47807949742732,
                -10.07026748604698,
                180.95318188920962
            ],
            "color": "#00FF00",
            "type": "post",
            "connected_node": [
                "category378"
            ]
        },
        {
            "id": "post36",
            "url": "blank",
            "position": [
                45.05639400081972,
                -22.999986824754963,
                181.31831448988368
            ],
            "color": "#00FF00",
            "type": "post",
            "connected_node": [
                "category378"
            ]
        },
        {
            "id": "post37",
            "url": "blank",
            "position": [
                45.05146902471114,
                -18.01510663333152,
                182.49354249293418
            ],
            "color": "#00FF00",
            "type": "post",
            "connected_node": [
                "category378"
            ]
        },
        {
            "id": "post38",
            "url": "blank",
            "position": [
                61.86248948204644,
                -7.704784381270105,
                175.13312364739264
            ],
            "color": "#00FF00",
            "type": "post",
            "connected_node": [
                "category378"
            ]
        },
        {
            "id": "post39",
            "url": "blank",
            "position": [
                77.63643305896908,
                -29.70171639590105,
                167.86581997621062
            ],
            "color": "#00FF00",
            "type": "post",
            "connected_node": [
                "category378"
            ]
        },
        {
            "id": "post40",
            "url": "blank",
            "position": [
                62.856732478539755,
                -46.09593973707888,
                171.14751035192856
            ],
            "color": "#00FF00",
            "type": "post",
            "connected_node": [
                "category378"
            ]
        },
        {
            "id": "post41",
            "url": "blank",
            "position": [
                70.89793429778786,
                -12.299295118866802,
                167.86174111301477
            ],
            "color": "#00FF00",
            "type": "post",
            "connected_node": [
                "category378"
            ]
        },
        {
            "id": "post42",
            "url": "blank",
            "position": [
                60.622852164381506,
                -6.666348906146897,
                179.35836587272252
            ],
            "color": "#00FF00",
            "type": "post",
            "connected_node": [
                "category378"
            ]
        },
        {
            "id": "post43",
            "url": "blank",
            "position": [
                51.358591182655275,
                -10.336127376387672,
                183.04225887967803
            ],
            "color": "#00FF00",
            "type": "post",
            "connected_node": [
                "category378"
            ]
        },
        {
            "id": "post44",
            "url": "blank",
            "position": [
                40.39446486350981,
                -17.777125526580548,
                183.39502259065893
            ],
            "color": "#00FF00",
            "type": "post",
            "connected_node": [
                "category378"
            ]
        },
        {
            "id": "post45",
            "url": "blank",
            "position": [
                39.34127783087895,
                -29.13990317401243,
                182.14680696076124
            ],
            "color": "#00FF00",
            "type": "post",
            "connected_node": [
                "category378"
            ]
        },
        {
            "id": "post46",
            "url": "blank",
            "position": [
                79.76307511881755,
                -36.39962558981017,
                167.42189475000487
            ],
            "color": "#00FF00",
            "type": "post",
            "connected_node": [
                "category378"
            ]
        },
        {
            "id": "post47",
            "url": "blank",
            "position": [
                76.30275145143585,
                -43.19397622492825,
                166.33902662555118
            ],
            "color": "#00FF00",
            "type": "post",
            "connected_node": [
                "category378"
            ]
        },
        {
            "id": "post48",
            "url": "blank",
            "position": [
                72.77132833866342,
                -46.017378494888135,
                167.59386886986547
            ],
            "color": "#00FF00",
            "type": "post",
            "connected_node": [
                "category378"
            ]
        },
        {
            "id": "post49",
            "url": "blank",
            "position": [
                44.96469141753935,
                -12.253668864791003,
                182.7267066167723
            ],
            "color": "#00FF00",
            "type": "post",
            "connected_node": [
                "category378"
            ]
        },
        {
            "id": "post50",
            "url": "blank",
            "position": [
                39.66153261215852,
                -38.79351789220946,
                174.24694321777193
            ],
            "color": "#00FF00",
            "type": "post",
            "connected_node": [
                "category378"
            ]
        },
        {
            "id": "post51",
            "url": "blank",
            "position": [
                39.95995864820562,
                -39.87897035378875,
                181.68218687894904
            ],
            "color": "#00FF00",
            "type": "post",
            "connected_node": [
                "category378"
            ]
        },
        {
            "id": "post52",
            "url": "blank",
            "position": [
                50.13022978659737,
                -46.6889307978109,
                176.291595838983
            ],
            "color": "#00FF00",
            "type": "post",
            "connected_node": [
                "category378"
            ]
        },
        {
            "id": "post53",
            "url": "blank",
            "position": [
                45.1559986019211,
                -7.471441656334807,
                185.8984064996494
            ],
            "color": "#00FF00",
            "type": "post",
            "connected_node": [
                "category378"
            ]
        },
        {
            "id": "post54",
            "url": "blank",
            "position": [
                36.79933914584838,
                -24.680461556815473,
                182.90844677312373
            ],
            "color": "#00FF00",
            "type": "post",
            "connected_node": [
                "category378"
            ]
        },
        {
            "id": "post55",
            "url": "blank",
            "position": [
                39.194662851537174,
                -13.47013791013844,
                183.79559480035155
            ],
            "color": "#00FF00",
            "type": "post",
            "connected_node": [
                "category378"
            ]
        },
        {
            "id": "post56",
            "url": "blank",
            "position": [
                72.23368238702312,
                -3.756630272853048,
                177.60814956762246
            ],
            "color": "#00FF00",
            "type": "post",
            "connected_node": [
                "category378"
            ]
        },
        {
            "id": "post57",
            "url": "blank",
            "position": [
                75.39899338996673,
                -8.065948475917242,
                172.91819749964313
            ],
            "color": "#00FF00",
            "type": "post",
            "connected_node": [
                "category378"
            ]
        },
        {
            "id": "post58",
            "url": "blank",
            "position": [
                45.8768312114575,
                -47.34784176607477,
                180.80577452207956
            ],
            "color": "#00FF00",
            "type": "post",
            "connected_node": [
                "category378"
            ]
        },
        {
            "id": "post59",
            "url": "blank",
            "position": [
                54.85794861901176,
                -52.12805723617211,
                169.28760631078998
            ],
            "color": "#00FF00",
            "type": "post",
            "connected_node": [
                "category378"
            ]
        },
        {
            "id": "post60",
            "url": "blank",
            "position": [
                57.89976180625043,
                0.6339557820157644,
                175.54971799029218
            ],
            "color": "#00FF00",
            "type": "post",
            "connected_node": [
                "category378"
            ]
        },
        {
            "id": "post61",
            "url": "blank",
            "position": [
                55.069140622265536,
                -1.6285012482129027,
                177.55524705238878
            ],
            "color": "#00FF00",
            "type": "post",
            "connected_node": [
                "category378"
            ]
        },
        {
            "id": "post62",
            "url": "blank",
            "position": [
                51.82727946130473,
                -1.73850249778938,
                180.40229660492193
            ],
            "color": "#00FF00",
            "type": "post",
            "connected_node": [
                "category378"
            ]
        },
        {
            "id": "post63",
            "url": "blank",
            "position": [
                36.25519411398829,
                -19.671017014945125,
                184.04762530968617
            ],
            "color": "#00FF00",
            "type": "post",
            "connected_node": [
                "category378"
            ]
        },
        {
            "id": "post64",
            "url": "blank",
            "position": [
                61.685023180891164,
                -51.610846662313406,
                166.02182480570875
            ],
            "color": "#00FF00",
            "type": "post",
            "connected_node": [
                "category378"
            ]
        },
        {
            "id": "post65",
            "url": "blank",
            "position": [
                42.5086466571923,
                -49.99010357435611,
                174.84564454557906
            ],
            "color": "#00FF00",
            "type": "post",
            "connected_node": [
                "category378"
            ]
        },
        {
            "id": "post66",
            "url": "blank",
            "position": [
                84.87264305033175,
                -36.01233546806938,
                165.5089606239155
            ],
            "color": "#00FF00",
            "type": "post",
            "connected_node": [
                "category378"
            ]
        },
        {
            "id": "post67",
            "url": "blank",
            "position": [
                81.99481518305956,
                -10.889719618021887,
                171.22628300893035
            ],
            "color": "#00FF00",
            "type": "post",
            "connected_node": [
                "category378"
            ]
        },
        {
            "id": "post68",
            "url": "blank",
            "position": [
                58.46735125536679,
                -0.2509749268885919,
                187.05145265382646
            ],
            "color": "#00FF00",
            "type": "post",
            "connected_node": [
                "category378"
            ]
        },
        {
            "id": "post69",
            "url": "blank",
            "position": [
                83.85698010351905,
                -43.008502003667544,
                166.71723869397272
            ],
            "color": "#00FF00",
            "type": "post",
            "connected_node": [
                "category378"
            ]
        },
        {
            "id": "post70",
            "url": "blank",
            "position": [
                81.14460785857842,
                -10.570182128046497,
                164.1771934660393
            ],
            "color": "#00FF00",
            "type": "post",
            "connected_node": [
                "category378"
            ]
        },
        {
            "id": "post71",
            "url": "blank",
            "position": [
                31.657954145564332,
                -28.832827773198417,
                183.56805127867625
            ],
            "color": "#00FF00",
            "type": "post",
            "connected_node": [
                "category378"
            ]
        },
        {
            "id": "post72",
            "url": "blank",
            "position": [
                32.30390939248615,
                -35.99139497467586,
                186.48701746607458
            ],
            "color": "#00FF00",
            "type": "post",
            "connected_node": [
                "category378"
            ]
        },
        {
            "id": "post73",
            "url": "blank",
            "position": [
                51.170021551015324,
                -57.464678930654415,
                171.3256548717626
            ],
            "color": "#00FF00",
            "type": "post",
            "connected_node": [
                "category378"
            ]
        },
        {
            "id": "post74",
            "url": "blank",
            "position": [
                39.33104060487496,
                -48.024958895880395,
                184.9526793825734
            ],
            "color": "#00FF00",
            "type": "post",
            "connected_node": [
                "category378"
            ]
        },
        {
            "id": "post75",
            "url": "blank",
            "position": [
                90.8720305274571,
                -26.245685774173882,
                166.24266556975715
            ],
            "color": "#00FF00",
            "type": "post",
            "connected_node": [
                "category378"
            ]
        },
        {
            "id": "post76",
            "url": "blank",
            "position": [
                29.974050075063737,
                -34.330977934616655,
                181.31075935992212
            ],
            "color": "#00FF00",
            "type": "post",
            "connected_node": [
                "category378"
            ]
        },
        {
            "id": "post77",
            "url": "blank",
            "position": [
                92.12047103381457,
                -19.779066978512056,
                171.29667473525038
            ],
            "color": "#00FF00",
            "type": "post",
            "connected_node": [
                "category378"
            ]
        },
        {
            "id": "post78",
            "url": "blank",
            "position": [
                90.80163124851269,
                -31.187233774952908,
                166.25328317570572
            ],
            "color": "#00FF00",
            "type": "post",
            "connected_node": [
                "category378"
            ]
        },
        {
            "id": "post79",
            "url": "blank",
            "position": [
                31.25253688378848,
                -13.851804324975546,
                187.15350653048642
            ],
            "color": "#00FF00",
            "type": "post",
            "connected_node": [
                "category378"
            ]
        }
    ]
}