{
    "node_list": [
        {
            "id": "post0",
            "url": "blank",
            "position": [
                22.393179601047127,
                112.74444354083626,
                44.2406230686382
            ],
            "color": "#00FF00",
            "type": "post",
            "connected_node": [
                "category188"
            ]
        },
        {
            "id": "post1",
            "url": "blank",
            "position": [
                20.259046833994535,
                114.90887114644289,
                40.828435170928806
            ],
            "color": "#00FF00",
            "type": "post",
            "connected_node": [
                "category188"
            ]
        },
        {
            "id": "post2",
            "url": "blank",
            "position": [
                16.035812956238733,
                116.33533240997802,
                42.53103635038903
            ],
            "color": "#00FF00",
            "type": "post",
            "connected_node": [
                "category188"
            ]
        },
        {
            "id": "post3",
            "url": "blank",
            "position": [
                24.18101968987352,
                113.85558538301835,
                39.55058811323324
            ],
            "color": "#00FF00",
            "type": "post",
            "connected_node": [
                "category188"
            ]
        },
        {
            "id": "post4",
            "url": "blank",
            "position": [
                18.43772789009877,
                117.20771335401194,
                37.92751895304083
            ],
            "color": "#00FF00",
            "type": "post",
            "connected_node": [
                "category188"
            ]
        },
        {
            "id": "post5",
            "url": "blank",
            "position": [
                22.350856211257852,
                116.05609505817095,
                36.48526886866001
            ],
            "color": "#00FF00",
            "type": "post",
            "connected_node": [
                "category188"
            ]
        },
        {
            "id": "post6",
            "url": "blank",
            "position": [
                28.174815575862503,
                114.36392981164525,
                40.30546199860152
            ],
            "color": "#00FF00",
            "type": "post",
            "connected_node": [
                "category188"
            ]
        },
        {
            "id": "post7",
            "url": "blank",
            "position": [
                29.452006797505927,
                110.77919851224642,
                41.735717301903726
            ],
            "color": "#00FF00",
            "type": "post",
            "connected_node": [
                "category188"
            ]
        },
        {
            "id": "post8",
            "url": "blank",
            "position": [
                19.84239250873837,
                111.06107547319841,
                51.104646610613635
            ],
            "color": "#00FF00",
            "type": "post",
            "connected_node": [
                "category188"
            ]
        },
        {
            "id": "post9",
            "url": "blank",
            "position": [
                14.44886690288341,
                111.76178569537433,
                47.22418850959532
            ],
            "color": "#00FF00",
            "type": "post",
            "connected_node": [
                "category188"
            ]
        },
        {
            "id": "post10",
            "url": "blank",
            "position": [
                13.03509885306685,
                119.18068773573026,
                40.265231920536884
            ],
            "color": "#00FF00",
            "type": "post",
            "connected_node": [
                "category188"
            ]
        },
        {
            "id": "post11",
            "url": "blank",
            "position": [
                15.778652521185379,
                119.19233895788233,
                35.61841597463306
            ],
            "color": "#00FF00",
            "type": "post",
            "connected_node": [
                "category188"
            ]
        },
        {
            "id": "post12",
            "url": "blank",
            "position": [
                11.996532658032383,
                114.82565702375871,
                39.93853175293279
            ],
            "color": "#00FF00",
            "type": "post",
            "connected_node": [
                "category188"
            ]
        },
        {
            "id": "post13",
            "url": "blank",
            "position": [
                28.415813827323134,
                115.90593368231707,
                34.7050821539232
            ],
            "color": "#00FF00",
            "type": "post",
            "connected_node": [
                "category188"
            ]
        },
        {
            "id": "post14",
            "url": "blank",
            "position": [
                24.405465467633796,
                108.81036448043422,
                53.92457822439604
            ],
            "color": "#00FF00",
            "type": "post",
            "connected_node": [
                "category188"
            ]
        },
        {
            "id": "post15",
            "url": "blank",
            "position": [
                29.052393454029456,
                108.79200199539275,
                50.8476605285812
            ],
            "color": "#00FF00",
            "type": "post",
            "connected_node": [
                "category188"
            ]
        },
        {
            "id": "post16",
            "url": "blank",
            "position": [
                17.717899720757934,
                120.37941282050845,
                30.876982609372973
            ],
            "color": "#00FF00",
            "type": "post",
            "connected_node": [
                "category188"
            ]
        },
        {
            "id": "post17",
            "url": "blank",
            "position": [
                33.626155172718455,
                107.69844504975731,
                46.16817185985752
            ],
            "color": "#00FF00",
            "type": "post",
            "connected_node": [
                "category188"
            ]
        },
        {
            "id": "post18",
            "url": "blank",
            "position": [
                35.397980124811006,
                110.03915834207537,
                42.09010691286889
            ],
            "color": "#00FF00",
            "type": "post",
            "connected_node": [
                "category188"
            ]
        },
        {
            "id": "post19",
            "url": "blank",
            "position": [
                6.151014916694173,
                113.1403194819918,
                46.16886083147035
            ],
            "color": "#00FF00",
            "type": "post",
            "connected_node": [
                "category188"
            ]
        },
        {
            "id": "post20",
            "url": "blank",
            "position": [
                9.093502990117718,
                121.08432028756783,
                38.01394922025708
            ],
            "color": "#00FF00",
            "type": "post",
            "connected_node": [
                "category188"
            ]
        },
        {
            "id": "post21",
            "url": "blank",
            "position": [
                25.404056528082393,
                119.41850321983073,
                29.592363994302605
            ],
            "color": "#00FF00",
            "type": "post",
            "connected_node": [
                "category188"
            ]
        },
        {
            "id": "post22",
            "url": "blank",
            "position": [
                36.031468797455666,
                113.63697683186288,
                37.969965111246196
            ],
            "color": "#00FF00",
            "type": "post",
            "connected_node": [
                "category188"
            ]
        },
        {
            "id": "post23",
            "url": "blank",
            "position": [
                6.30767115458656,
                121.51343858044798,
                46.73557054470789
            ],
            "color": "#00FF00",
            "type": "post",
            "connected_node": [
                "category188"
            ]
        },
        {
            "id": "post24",
            "url": "blank",
            "position": [
                16.287587634205934,
                121.10199322894337,
                27.043112968436574
            ],
            "color": "#00FF00",
            "type": "post",
            "connected_node": [
                "category188"
            ]
        },
        {
            "id": "post25",
            "url": "blank",
            "position": [
                28.071598285526523,
                108.63288112416556,
                55.821292420402514
            ],
            "color": "#00FF00",
            "type": "post",
            "connected_node": [
                "category188"
            ]
        },
        {
            "id": "post26",
            "url": "blank",
            "position": [
                13.035124848409676,
                119.05337245386364,
                28.895547701372376
            ],
            "color": "#00FF00",
            "type": "post",
            "connected_node": [
                "category188"
            ]
        },
        {
            "id": "post27",
            "url": "blank",
            "position": [
                9.150463141700492,
                112.7610645963672,
                53.562458469655255
            ],
            "color": "#00FF00",
            "type": "post",
            "connected_node": [
                "category188"
            ]
        },
        {
            "id": "post28",
            "url": "blank",
            "position": [
                19.865861862483587,
                108.1721762311721,
                59.288818605484835
            ],
            "color": "#00FF00",
            "type": "post",
            "connected_node": [
                "category188"
            ]
        },
        {
            "id": "post29",
            "url": "blank",
            "position": [
                22.044176684701473,
                120.49710120112088,
                25.46195239303052
            ],
            "color": "#00FF00",
            "type": "post",
            "connected_node": [
                "category188"
            ]
        },
        {
            "id": "post30",
            "url": "blank",
            "position": [
                1.667135737331293,
                115.0705925571588,
                39.320715234253505
            ],
            "color": "#00FF00",
            "type": "post",
            "connected_node": [
                "category188"
            ]
        },
        {
            "id": "post31",
            "url": "blank",
            "position": [
                39.49765116408739,
                109.80447421352997,
                36.27314817127305
            ],
            "color": "#00FF00",
            "type": "post",
            "connected_node": [
                "category188"
            ]
        },
        {
            "id": "post32",
            "url": "blank",
            "position": [
                2.8518438412525704,
                119.93683588163472,
                35.751520908963684
            ],
            "color": "#00FF00",
            "type": "post",
            "connected_node": [
                "category188"
            ]
        },
        {
            "id": "post33",
            "url": "blank",
            "position": [
                35.025951412107304,
                111.71999095874365,
                27.43949019926088
            ],
            "color": "#00FF00",
            "type": "post",
            "connected_node": [
                "category188"
            ]
        },
        {
            "id": "post34",
            "url": "blank",
            "position": [
                1.1731254296227753,
                117.43584833277932,
                51.376215657212974
            ],
            "color": "#00FF00",
            "type": "post",
            "connected_node": [
                "category188"
            ]
        },
        {
            "id": "post35",
            "url": "blank",
            "position": [
                24.542024285682963,
                120.98434526352408,
                21.698669027562488
            ],
            "color": "#00FF00",
            "type": "post",
            "connected_node": [
                "category188"
            ]
        },
        {
            "id": "post36",
            "url": "blank",
            "position": [
                38.85872505919302,
                116.593176518588,
                32.43675197655428
            ],
            "color": "#00FF00",
            "type": "post",
            "connected_node": [
                "category188"
            ]
        },
        {
            "id": "post37",
            "url": "blank",
            "position": [
                39.210841784372676,
                102.22059342227831,
                50.52327109198922
            ],
            "color": "#00FF00",
            "type": "post",
            "connected_node": [
                "category188"
            ]
        },
        {
            "id": "post38",
            "url": "blank",
            "position": [
                0.971767396400935,
                108.4354892741387,
                52.931723142975095
            ],
            "color": "#00FF00",
            "type": "post",
            "connected_node": [
                "category188"
            ]
        },
        {
            "id": "post39",
            "url": "blank",
            "position": [
                0.7842299568585673,
                112.48601571676807,
                52.34078040252608
            ],
            "color": "#00FF00",
            "type": "post",
            "connected_node": [
                "category188"
            ]
        }
    ]
}