{
    "node_list": [
        {
            "id": "post0",
            "url": "blank",
            "position": [
                -78.74808571235734,
                -38.170029526367635,
                83.2536191261282
            ],
            "color": "#00FF00",
            "type": "post",
            "connected_node": [
                "category179"
            ]
        },
        {
            "id": "post1",
            "url": "blank",
            "position": [
                -75.5657730032741,
                -43.78093404373975,
                82.5078542355773
            ],
            "color": "#00FF00",
            "type": "post",
            "connected_node": [
                "category179"
            ]
        },
        {
            "id": "post2",
            "url": "blank",
            "position": [
                -80.66033408999871,
                -36.14570132960726,
                79.09375920913129
            ],
            "color": "#00FF00",
            "type": "post",
            "connected_node": [
                "category179"
            ]
        },
        {
            "id": "post3",
            "url": "blank",
            "position": [
                -78.06973939687569,
                -45.28309896242904,
                77.80463331764058
            ],
            "color": "#00FF00",
            "type": "post",
            "connected_node": [
                "category179"
            ]
        },
        {
            "id": "post4",
            "url": "blank",
            "position": [
                -82.58493250827453,
                -42.399611656007394,
                76.33155552385716
            ],
            "color": "#00FF00",
            "type": "post",
            "connected_node": [
                "category179"
            ]
        },
        {
            "id": "post5",
            "url": "blank",
            "position": [
                -72.24385376885695,
                -49.06515419998789,
                79.55735447864352
            ],
            "color": "#00FF00",
            "type": "post",
            "connected_node": [
                "category179"
            ]
        },
        {
            "id": "post6",
            "url": "blank",
            "position": [
                -73.80653638275244,
                -35.552578767734175,
                87.03336108233228
            ],
            "color": "#00FF00",
            "type": "post",
            "connected_node": [
                "category179"
            ]
        },
        {
            "id": "post7",
            "url": "blank",
            "position": [
                -79.42534704282234,
                -50.4501109898806,
                75.75392489643053
            ],
            "color": "#00FF00",
            "type": "post",
            "connected_node": [
                "category179"
            ]
        },
        {
            "id": "post8",
            "url": "blank",
            "position": [
                -85.7432053986763,
                -34.252575293898765,
                79.60814735735377
            ],
            "color": "#00FF00",
            "type": "post",
            "connected_node": [
                "category179"
            ]
        },
        {
            "id": "post9",
            "url": "blank",
            "position": [
                -78.79192386022615,
                -30.830068728934357,
                82.16984660546618
            ],
            "color": "#00FF00",
            "type": "post",
            "connected_node": [
                "category179"
            ]
        },
        {
            "id": "post10",
            "url": "blank",
            "position": [
                -86.51336883133868,
                -33.99651227122804,
                74.1412993324945
            ],
            "color": "#00FF00",
            "type": "post",
            "connected_node": [
                "category179"
            ]
        },
        {
            "id": "post11",
            "url": "blank",
            "position": [
                -85.94494322209233,
                -47.055818723188096,
                71.1297795278312
            ],
            "color": "#00FF00",
            "type": "post",
            "connected_node": [
                "category179"
            ]
        },
        {
            "id": "post12",
            "url": "blank",
            "position": [
                -74.72587458330692,
                -30.452474553940856,
                87.22994870681907
            ],
            "color": "#00FF00",
            "type": "post",
            "connected_node": [
                "category179"
            ]
        },
        {
            "id": "post13",
            "url": "blank",
            "position": [
                -66.91301365077122,
                -49.05419314891447,
                88.989185078783
            ],
            "color": "#00FF00",
            "type": "post",
            "connected_node": [
                "category179"
            ]
        },
        {
            "id": "post14",
            "url": "blank",
            "position": [
                -68.51994530566809,
                -36.45594408745166,
                93.13568973912916
            ],
            "color": "#00FF00",
            "type": "post",
            "connected_node": [
                "category179"
            ]
        },
        {
            "id": "post15",
            "url": "blank",
            "position": [
                -80.70929605025029,
                -26.626518388826163,
                88.76317448355148
            ],
            "color": "#00FF00",
            "type": "post",
            "connected_node": [
                "category179"
            ]
        },
        {
            "id": "post16",
            "url": "blank",
            "position": [
                -90.57659986272392,
                -32.25933181246243,
                77.62755450027467
            ],
            "color": "#00FF00",
            "type": "post",
            "connected_node": [
                "category179"
            ]
        },
        {
            "id": "post17",
            "url": "blank",
            "position": [
                -70.96895044355483,
                -30.78947035828675,
                91.20653319300413
            ],
            "color": "#00FF00",
            "type": "post",
            "connected_node": [
                "category179"
            ]
        },
        {
            "id": "post18",
            "url": "blank",
            "position": [
                -80.39198983798367,
                -56.855276903812104,
                78.0069909809119
            ],
            "color": "#00FF00",
            "type": "post",
            "connected_node": [
                "category179"
            ]
        },
        {
            "id": "post19",
            "url": "blank",
            "position": [
                -75.90624061199948,
                -27.549189224717573,
                92.26687979161822
            ],
            "color": "#00FF00",
            "type": "post",
            "connected_node": [
                "category179"
            ]
        },
        {
            "id": "post20",
            "url": "blank",
            "position": [
                -90.87886595217668,
                -37.82710486310807,
                70.31545974575027
            ],
            "color": "#00FF00",
            "type": "post",
            "connected_node": [
                "category179"
            ]
        },
        {
            "id": "post21",
            "url": "blank",
            "position": [
                -87.64095688080744,
                -50.87220244974608,
                68.97832229380916
            ],
            "color": "#00FF00",
            "type": "post",
            "connected_node": [
                "category179"
            ]
        },
        {
            "id": "post22",
            "url": "blank",
            "position": [
                -83.302375957842,
                -56.54298226683471,
                71.21581047852034
            ],
            "color": "#00FF00",
            "type": "post",
            "connected_node": [
                "category179"
            ]
        },
        {
            "id": "post23",
            "url": "blank",
            "position": [
                -64.22535163550342,
                -52.091725412106314,
                92.58498563302294
            ],
            "color": "#00FF00",
            "type": "post",
            "connected_node": [
                "category179"
            ]
        },
        {
            "id": "post24",
            "url": "blank",
            "position": [
                -92.21957761658668,
                -44.14829586305848,
                65.55321900012858
            ],
            "color": "#00FF00",
            "type": "post",
            "connected_node": [
                "category179"
            ]
        },
        {
            "id": "post25",
            "url": "blank",
            "position": [
                -62.3655470194271,
                -55.608174791598735,
                84.24514398988019
            ],
            "color": "#00FF00",
            "type": "post",
            "connected_node": [
                "category179"
            ]
        },
        {
            "id": "post26",
            "url": "blank",
            "position": [
                -90.13371100361674,
                -23.503370250623497,
                73.22084123737046
            ],
            "color": "#00FF00",
            "type": "post",
            "connected_node": [
                "category179"
            ]
        },
        {
            "id": "post27",
            "url": "blank",
            "position": [
                -91.86432526574976,
                -50.345564379514435,
                63.377151793263664
            ],
            "color": "#00FF00",
            "type": "post",
            "connected_node": [
                "category179"
            ]
        },
        {
            "id": "post28",
            "url": "blank",
            "position": [
                -85.07555471490615,
                -53.93181370764928,
                64.7841422434357
            ],
            "color": "#00FF00",
            "type": "post",
            "connected_node": [
                "category179"
            ]
        },
        {
            "id": "post29",
            "url": "blank",
            "position": [
                -64.73994962702662,
                -57.447212999420096,
                87.61574288811273
            ],
            "color": "#00FF00",
            "type": "post",
            "connected_node": [
                "category179"
            ]
        },
        {
            "id": "post30",
            "url": "blank",
            "position": [
                -81.03570073156074,
                -21.699677117193644,
                91.97246320361577
            ],
            "color": "#00FF00",
            "type": "post",
            "connected_node": [
                "category179"
            ]
        },
        {
            "id": "post31",
            "url": "blank",
            "position": [
                -95.91987358105712,
                -38.31631201348415,
                63.92180807914218
            ],
            "color": "#00FF00",
            "type": "post",
            "connected_node": [
                "category179"
            ]
        },
        {
            "id": "post32",
            "url": "blank",
            "position": [
                -65.33273271286666,
                -58.68891221641266,
                91.50995283208657
            ],
            "color": "#00FF00",
            "type": "post",
            "connected_node": [
                "category179"
            ]
        },
        {
            "id": "post33",
            "url": "blank",
            "position": [
                -60.090125234734174,
                -47.02241912993324,
                93.98095540032189
            ],
            "color": "#00FF00",
            "type": "post",
            "connected_node": [
                "category179"
            ]
        },
        {
            "id": "post34",
            "url": "blank",
            "position": [
                -95.46494804755169,
                -34.70929420911021,
                66.60637385434639
            ],
            "color": "#00FF00",
            "type": "post",
            "connected_node": [
                "category179"
            ]
        },
        {
            "id": "post35",
            "url": "blank",
            "position": [
                -92.94787075417811,
                -26.265672816253737,
                67.9891842801586
            ],
            "color": "#00FF00",
            "type": "post",
            "connected_node": [
                "category179"
            ]
        },
        {
            "id": "post36",
            "url": "blank",
            "position": [
                -72.32468006413586,
                -61.109692496300106,
                71.00591648690933
            ],
            "color": "#00FF00",
            "type": "post",
            "connected_node": [
                "category179"
            ]
        },
        {
            "id": "post37",
            "url": "blank",
            "position": [
                -66.79901049747126,
                -62.46589377789692,
                83.29742306047882
            ],
            "color": "#00FF00",
            "type": "post",
            "connected_node": [
                "category179"
            ]
        },
        {
            "id": "post38",
            "url": "blank",
            "position": [
                -62.424726530100344,
                -41.73409576294293,
                96.34866973499665
            ],
            "color": "#00FF00",
            "type": "post",
            "connected_node": [
                "category179"
            ]
        },
        {
            "id": "post39",
            "url": "blank",
            "position": [
                -96.84911603057509,
                -28.94625627241321,
                70.61279463818403
            ],
            "color": "#00FF00",
            "type": "post",
            "connected_node": [
                "category179"
            ]
        },
        {
            "id": "post40",
            "url": "blank",
            "position": [
                -86.51310383301687,
                -60.28556692478155,
                69.01094285981188
            ],
            "color": "#00FF00",
            "type": "post",
            "connected_node": [
                "category179"
            ]
        },
        {
            "id": "post41",
            "url": "blank",
            "position": [
                -95.38831251336745,
                -21.698997002805157,
                80.40560585697757
            ],
            "color": "#00FF00",
            "type": "post",
            "connected_node": [
                "category179"
            ]
        },
        {
            "id": "post42",
            "url": "blank",
            "position": [
                -69.84809062306118,
                -63.63286952734492,
                86.91220968463634
            ],
            "color": "#00FF00",
            "type": "post",
            "connected_node": [
                "category179"
            ]
        },
        {
            "id": "post43",
            "url": "blank",
            "position": [
                -82.76961003570895,
                -62.59968733562374,
                73.87843935812839
            ],
            "color": "#00FF00",
            "type": "post",
            "connected_node": [
                "category179"
            ]
        },
        {
            "id": "post44",
            "url": "blank",
            "position": [
                -100.45095034715636,
                -34.43539031333773,
                69.59345893424513
            ],
            "color": "#00FF00",
            "type": "post",
            "connected_node": [
                "category179"
            ]
        },
        {
            "id": "post45",
            "url": "blank",
            "position": [
                -71.26658483098312,
                -25.734306207524032,
                97.61122025818703
            ],
            "color": "#00FF00",
            "type": "post",
            "connected_node": [
                "category179"
            ]
        },
        {
            "id": "post46",
            "url": "blank",
            "position": [
                -83.78999150733293,
                -57.715621520115754,
                62.433283868177945
            ],
            "color": "#00FF00",
            "type": "post",
            "connected_node": [
                "category179"
            ]
        },
        {
            "id": "post47",
            "url": "blank",
            "position": [
                -61.37333027167067,
                -61.58598416710541,
                79.15750930544749
            ],
            "color": "#00FF00",
            "type": "post",
            "connected_node": [
                "category179"
            ]
        },
        {
            "id": "post48",
            "url": "blank",
            "position": [
                -88.08552918958803,
                -17.044640211237606,
                88.62820888832121
            ],
            "color": "#00FF00",
            "type": "post",
            "connected_node": [
                "category179"
            ]
        },
        {
            "id": "post49",
            "url": "blank",
            "position": [
                -57.569394187741565,
                -54.64589165531268,
                88.29951722799538
            ],
            "color": "#00FF00",
            "type": "post",
            "connected_node": [
                "category179"
            ]
        },
        {
            "id": "post50",
            "url": "blank",
            "position": [
                -58.527259424771884,
                -50.33020281009136,
                96.1386444617582
            ],
            "color": "#00FF00",
            "type": "post",
            "connected_node": [
                "category179"
            ]
        },
        {
            "id": "post51",
            "url": "blank",
            "position": [
                -97.14375063775972,
                -44.137116492512064,
                60.836280197649316
            ],
            "color": "#00FF00",
            "type": "post",
            "connected_node": [
                "category179"
            ]
        },
        {
            "id": "post52",
            "url": "blank",
            "position": [
                -90.8617991255139,
                -53.94495330611533,
                60.8743849892967
            ],
            "color": "#00FF00",
            "type": "post",
            "connected_node": [
                "category179"
            ]
        },
        {
            "id": "post53",
            "url": "blank",
            "position": [
                -63.59414038843676,
                -33.49011541770977,
                99.20835731321787
            ],
            "color": "#00FF00",
            "type": "post",
            "connected_node": [
                "category179"
            ]
        },
        {
            "id": "post54",
            "url": "blank",
            "position": [
                -57.314448562493794,
                -50.401052446936156,
                91.33261085183408
            ],
            "color": "#00FF00",
            "type": "post",
            "connected_node": [
                "category179"
            ]
        },
        {
            "id": "post55",
            "url": "blank",
            "position": [
                -58.73723169971461,
                -39.71489061079676,
                100.05574869424095
            ],
            "color": "#00FF00",
            "type": "post",
            "connected_node": [
                "category179"
            ]
        },
        {
            "id": "post56",
            "url": "blank",
            "position": [
                -75.81731964548578,
                -19.487048210964975,
                97.16369682627283
            ],
            "color": "#00FF00",
            "type": "post",
            "connected_node": [
                "category179"
            ]
        },
        {
            "id": "post57",
            "url": "blank",
            "position": [
                -79.7080658759867,
                -67.39700241901816,
                72.08874724494034
            ],
            "color": "#00FF00",
            "type": "post",
            "connected_node": [
                "category179"
            ]
        },
        {
            "id": "post58",
            "url": "blank",
            "position": [
                -66.04038556043663,
                -25.028273686737613,
                100.84910075953772
            ],
            "color": "#00FF00",
            "type": "post",
            "connected_node": [
                "category179"
            ]
        },
        {
            "id": "post59",
            "url": "blank",
            "position": [
                -102.80022194666003,
                -28.04995817805586,
                74.87767173393505
            ],
            "color": "#00FF00",
            "type": "post",
            "connected_node": [
                "category179"
            ]
        },
        {
            "id": "post60",
            "url": "blank",
            "position": [
                -83.58282083616582,
                -18.176202181705907,
                94.25792827745983
            ],
            "color": "#00FF00",
            "type": "post",
            "connected_node": [
                "category179"
            ]
        },
        {
            "id": "post61",
            "url": "blank",
            "position": [
                -60.443531748511845,
                -49.62932376628755,
                101.89530406956865
            ],
            "color": "#00FF00",
            "type": "post",
            "connected_node": [
                "category179"
            ]
        },
        {
            "id": "post62",
            "url": "blank",
            "position": [
                -86.91238781264289,
                -12.925237598930611,
                80.2037620831385
            ],
            "color": "#00FF00",
            "type": "post",
            "connected_node": [
                "category179"
            ]
        },
        {
            "id": "post63",
            "url": "blank",
            "position": [
                -66.83371879514746,
                -20.178143484772406,
                96.2122297537652
            ],
            "color": "#00FF00",
            "type": "post",
            "connected_node": [
                "category179"
            ]
        },
        {
            "id": "post64",
            "url": "blank",
            "position": [
                -78.552999686595,
                -14.031745313469866,
                91.1446206360686
            ],
            "color": "#00FF00",
            "type": "post",
            "connected_node": [
                "category179"
            ]
        },
        {
            "id": "post65",
            "url": "blank",
            "position": [
                -56.47134550302637,
                -37.01545764048687,
                102.14255701375355
            ],
            "color": "#00FF00",
            "type": "post",
            "connected_node": [
                "category179"
            ]
        },
        {
            "id": "post66",
            "url": "blank",
            "position": [
                -88.89757785745371,
                -62.530186047338034,
                65.62042926671096
            ],
            "color": "#00FF00",
            "type": "post",
            "connected_node": [
                "category179"
            ]
        },
        {
            "id": "post67",
            "url": "blank",
            "position": [
                -61.82276781915847,
                -27.12364454433518,
                102.72882905084202
            ],
            "color": "#00FF00",
            "type": "post",
            "connected_node": [
                "category179"
            ]
        },
        {
            "id": "post68",
            "url": "blank",
            "position": [
                -83.30548427585089,
                -12.513366458018016,
                88.63702323648403
            ],
            "color": "#00FF00",
            "type": "post",
            "connected_node": [
                "category179"
            ]
        },
        {
            "id": "post69",
            "url": "blank",
            "position": [
                -58.36405875277927,
                -56.44494174090847,
                99.11758304352108
            ],
            "color": "#00FF00",
            "type": "post",
            "connected_node": [
                "category179"
            ]
        },
        {
            "id": "post70",
            "url": "blank",
            "position": [
                -101.48543057497662,
                -20.562074720977932,
                77.1250036864305
            ],
            "color": "#00FF00",
            "type": "post",
            "connected_node": [
                "category179"
            ]
        }
    ]
}